mixician/__init__.py
mixician/balancers/__init__.py
mixician/balancers/balance_with_probs.py
mixician/balancers/base.py
mixician/balancers/compute_divergence.py
mixician/calculators/__init__.py
mixician/calculators/base.py
mixician/calculators/calculate_with_components.py
mixician/calculators/calculate_with_self_balancing_components.py
mixician/calculators/limit_upper_bound.py
mixician/calculators/lognorm_to_power.py
mixician/dataloaders/__init__.py
mixician/dataloaders/base.py
mixician/dataloaders/load_config.py
mixician/dataloaders/load_dataframe.py
mixician/dataloaders/set_path.py
mixician/examples/__init__.py
mixician/examples/calculate_value_based_ensemble_score/config_case_01.yml
mixician/examples/calculate_value_based_ensemble_score/config_case_02.yml
mixician/examples/calculate_value_based_ensemble_score/config_case_03.yml
mixician/examples/calculate_value_based_ensemble_score/optimize_parameters_with_paradance.ipynb
mixician/examples/calculate_value_based_ensemble_score/self_balancing_value_based_ensemble_score.ipynb
mixician/examples/calculate_value_based_ensemble_score/value_based_ensemble_score.ipynb
mixician/examples/dataset/__init__.py
mixician/examples/dataset/utils.py
mixician/optimization/__init__.py
mixician/visualization/__init__.py
mixician/visualization/plot_distributions.py
mixician-0.1.20.dist-info/LICENSE
mixician-0.1.20.dist-info/METADATA
mixician-0.1.20.dist-info/WHEEL
mixician-0.1.20.dist-info/RECORD
